[{"name":"metadata.json","path":"dist/metadata.json","internal_type":30,"type":"Metadata"},{"name":"swobu.exe","path":"dist/swobu_windows_arm64_v8.0/swobu.exe","goos":"windows","goarch":"arm64","goarm64":"v8.0","target":"windows_arm64_v8.0","internal_type":4,"type":"Binary","extra":{"Binary":"swobu","Builder":"go","Ext":".exe","ID":"swobu"}},{"name":"swobu","path":"dist/swobu_linux_amd64_v1/swobu","goos":"linux","goarch":"amd64","goamd64":"v1","target":"linux_amd64_v1","internal_type":4,"type":"Binary","extra":{"Binary":"swobu","Builder":"go","Ext":"","ID":"swobu"}},{"name":"swobu","path":"dist/swobu_linux_arm64_v8.0/swobu","goos":"linux","goarch":"arm64","goarm64":"v8.0","target":"linux_arm64_v8.0","internal_type":4,"type":"Binary","extra":{"Binary":"swobu","Builder":"go","Ext":"","ID":"swobu"}},{"name":"swobu.exe","path":"dist/swobu_windows_amd64_v1/swobu.exe","goos":"windows","goarch":"amd64","goamd64":"v1","target":"windows_amd64_v1","internal_type":4,"type":"Binary","extra":{"Binary":"swobu","Builder":"go","Ext":".exe","ID":"swobu"}},{"name":"swobu","path":"dist/swobu_darwin_amd64_v1/swobu","goos":"darwin","goarch":"amd64","goamd64":"v1","target":"darwin_amd64_v1","internal_type":4,"type":"Binary","extra":{"Binary":"swobu","Builder":"go","Ext":"","ID":"swobu"}},{"name":"swobu","path":"dist/swobu_darwin_arm64_v8.0/swobu","goos":"darwin","goarch":"arm64","goarm64":"v8.0","target":"darwin_arm64_v8.0","internal_type":4,"type":"Binary","extra":{"Binary":"swobu","Builder":"go","Ext":"","ID":"swobu"}},{"name":"swobu_0.0.0-SNAPSHOT-none_windows_arm64.zip","path":"dist/swobu_0.0.0-SNAPSHOT-none_windows_arm64.zip","goos":"windows","goarch":"arm64","goarm64":"v8.0","target":"windows_arm64_v8.0","internal_type":1,"type":"Archive","extra":{"Binaries":["swobu.exe"],"Checksum":"sha256:b8dabe8a773bc598dafa3d4c189efe6c932fd853019c8e36f32adc2c4269be79","Format":"zip","ID":"swobu-archive","WrappedIn":""}},{"name":"swobu_0.0.0-SNAPSHOT-none_darwin_arm64.tar.gz","path":"dist/swobu_0.0.0-SNAPSHOT-none_darwin_arm64.tar.gz","goos":"darwin","goarch":"arm64","goarm64":"v8.0","target":"darwin_arm64_v8.0","internal_type":1,"type":"Archive","extra":{"Binaries":["swobu"],"Checksum":"sha256:4198202264b8e1dbde855236d287c8a0adc0b2f7a690c8804eaa5fa32fe4a102","Format":"tar.gz","ID":"swobu-archive","WrappedIn":""}},{"name":"swobu_0.0.0-SNAPSHOT-none_linux_arm64.tar.gz","path":"dist/swobu_0.0.0-SNAPSHOT-none_linux_arm64.tar.gz","goos":"linux","goarch":"arm64","goarm64":"v8.0","target":"linux_arm64_v8.0","internal_type":1,"type":"Archive","extra":{"Binaries":["swobu"],"Checksum":"sha256:1965c9b98a67e8fa6f71eeb54dafd3101d9933a02a78d342dc96aa0243007ae7","Format":"tar.gz","ID":"swobu-archive","WrappedIn":""}},{"name":"swobu_0.0.0-SNAPSHOT-none_windows_amd64.zip","path":"dist/swobu_0.0.0-SNAPSHOT-none_windows_amd64.zip","goos":"windows","goarch":"amd64","goamd64":"v1","target":"windows_amd64_v1","internal_type":1,"type":"Archive","extra":{"Binaries":["swobu.exe"],"Checksum":"sha256:266d064963744fa5ce7d27e099fb313668d668893095dd7dc89801f632bbacf4","Format":"zip","ID":"swobu-archive","WrappedIn":""}},{"name":"swobu_0.0.0-SNAPSHOT-none_darwin_amd64.tar.gz","path":"dist/swobu_0.0.0-SNAPSHOT-none_darwin_amd64.tar.gz","goos":"darwin","goarch":"amd64","goamd64":"v1","target":"darwin_amd64_v1","internal_type":1,"type":"Archive","extra":{"Binaries":["swobu"],"Checksum":"sha256:9d65368eb53347faded78e4994bbb46eff61d56098cc62e7617b2fb21b6f9272","Format":"tar.gz","ID":"swobu-archive","WrappedIn":""}},{"name":"swobu_0.0.0-SNAPSHOT-none_linux_amd64.tar.gz","path":"dist/swobu_0.0.0-SNAPSHOT-none_linux_amd64.tar.gz","goos":"linux","goarch":"amd64","goamd64":"v1","target":"linux_amd64_v1","internal_type":1,"type":"Archive","extra":{"Binaries":["swobu"],"Checksum":"sha256:9c17abe1b84dbda6ecefd43ccac3cfbaa6761c3e297b9a3769888e0e3351c040","Format":"tar.gz","ID":"swobu-archive","WrappedIn":""}},{"name":"checksums.txt","path":"dist/checksums.txt","internal_type":12,"type":"Checksum","extra":{}}]